{
  "@context": "http://iiif.io/api/image/3/context.json",
  "id": "https://nationalgalleryofart.github.io/accademia-iiif/documents/asrtncuff1516240901/e266a10b975d9a26797f9e83184e2763",
  "type": "ImageService3",
  "profile": "level0",
  "protocol": "http://iiif.io/api/image",
  "tiles": [
    {
      "scaleFactors": [
        1,
        2,
        4,
        8
      ],
      "width": 256
    }
  ],
  "width": 1584,
  "height": 2187,
  "sizes": [
    {
      "width": 218,
      "height": 300
    },
    {
      "width": 1449,
      "height": 2000
    }
  ]
}