{
  "@context": "http://iiif.io/api/image/3/context.json",
  "id": "https://nationalgalleryofart.github.io/accademia-iiif/documents/asrtcsvol054816310916/b0b02716078bd6f2930ed62fb555d2c5",
  "type": "ImageService3",
  "profile": "level0",
  "protocol": "http://iiif.io/api/image",
  "tiles": [
    {
      "scaleFactors": [
        1,
        2,
        4,
        8
      ],
      "width": 256
    }
  ],
  "width": 2428,
  "height": 3545,
  "sizes": [
    {
      "width": 205,
      "height": 300
    },
    {
      "width": 1370,
      "height": 2000
    }
  ]
}