{
  "@context": "http://iiif.io/api/image/3/context.json",
  "id": "https://nationalgalleryofart.github.io/accademia-iiif/documents/asrtncuff1516230129/1126464a46532a41ffa17f1e2b82d8a1",
  "type": "ImageService3",
  "profile": "level0",
  "protocol": "http://iiif.io/api/image",
  "tiles": [
    {
      "scaleFactors": [
        1,
        2,
        4,
        8
      ],
      "width": 256
    }
  ],
  "width": 1582,
  "height": 2114,
  "sizes": [
    {
      "width": 224,
      "height": 300
    },
    {
      "width": 1497,
      "height": 2000
    }
  ]
}