{
  "@context": "http://iiif.io/api/image/3/context.json",
  "id": "https://nationalgalleryofart.github.io/accademia-iiif/documents/asrtncuff1516300421/d59b21b2ebaae554b466880c51210cb6",
  "type": "ImageService3",
  "profile": "level0",
  "protocol": "http://iiif.io/api/image",
  "tiles": [
    {
      "scaleFactors": [
        1,
        2,
        4,
        8
      ],
      "width": 256
    }
  ],
  "width": 1702,
  "height": 2180,
  "sizes": [
    {
      "width": 234,
      "height": 300
    },
    {
      "width": 1561,
      "height": 2000
    }
  ]
}