{
  "@context": "http://iiif.io/api/image/3/context.json",
  "id": "https://nationalgalleryofart.github.io/accademia-iiif/documents/asrtncuff1516260624/7e07eb1e4ca1afea8bb040124ecd67f0",
  "type": "ImageService3",
  "profile": "level0",
  "protocol": "http://iiif.io/api/image",
  "tiles": [
    {
      "scaleFactors": [
        1,
        2,
        4,
        8
      ],
      "width": 256
    }
  ],
  "width": 1588,
  "height": 2168,
  "sizes": [
    {
      "width": 220,
      "height": 300
    },
    {
      "width": 1465,
      "height": 2000
    }
  ]
}