{
  "@context": "http://iiif.io/api/image/3/context.json",
  "id": "https://nationalgalleryofart.github.io/accademia-iiif/documents/asrtncuff1516230918b/324bf24567489971bc83d1d1010aad13",
  "type": "ImageService3",
  "profile": "level0",
  "protocol": "http://iiif.io/api/image",
  "tiles": [
    {
      "scaleFactors": [
        1,
        2,
        4,
        8
      ],
      "width": 256
    }
  ],
  "width": 1536,
  "height": 2128,
  "sizes": [
    {
      "width": 217,
      "height": 300
    },
    {
      "width": 1444,
      "height": 2000
    }
  ]
}