{
  "@context": "http://iiif.io/api/image/3/context.json",
  "id": "https://nationalgalleryofart.github.io/accademia-iiif/documents/asrtncuff1516320501/1ed0cb4848af6e8af774ee6a4fedc771",
  "type": "ImageService3",
  "profile": "level0",
  "protocol": "http://iiif.io/api/image",
  "tiles": [
    {
      "scaleFactors": [
        1,
        2,
        4,
        8
      ],
      "width": 256
    }
  ],
  "width": 1580,
  "height": 2168,
  "sizes": [
    {
      "width": 219,
      "height": 300
    },
    {
      "width": 1458,
      "height": 2000
    }
  ]
}