{
  "@context": "http://iiif.io/api/image/3/context.json",
  "id": "https://nationalgalleryofart.github.io/accademia-iiif/documents/asrtcsvol054216210618/b30efd97e3b575a2bc45b5489006ff62",
  "type": "ImageService3",
  "profile": "level0",
  "protocol": "http://iiif.io/api/image",
  "tiles": [
    {
      "scaleFactors": [
        1,
        2,
        4,
        8
      ],
      "width": 256
    }
  ],
  "width": 2061,
  "height": 2775,
  "sizes": [
    {
      "width": 223,
      "height": 300
    },
    {
      "width": 1485,
      "height": 2000
    }
  ]
}