{
  "@context": "http://iiif.io/api/image/3/context.json",
  "id": "https://nationalgalleryofart.github.io/accademia-iiif/documents/asrtcsvol054516290317/f9399f54018a944b21f8cd657875f6d5",
  "type": "ImageService3",
  "profile": "level0",
  "protocol": "http://iiif.io/api/image",
  "tiles": [
    {
      "scaleFactors": [
        1,
        2,
        4,
        8
      ],
      "width": 256
    }
  ],
  "width": 2322,
  "height": 3495,
  "sizes": [
    {
      "width": 200,
      "height": 300
    },
    {
      "width": 1329,
      "height": 2000
    }
  ]
}